fatlib/__init__.py
fatlib/_fairness.py
fatlib/_preprocessing.py
fatlib/_utils.py
fatlib/tests/test_preprocessing.py
fatlib/tests/test_utils.py
fatlib-0.1.0.dist-info/WHEEL
fatlib-0.1.0.dist-info/METADATA
fatlib-0.1.0.dist-info/RECORD
