Metadata-Version: 2.1
Name: fatlib
Version: 0.1.0
Summary: 
Author: Code4Thought
Author-email: support@code4thought.eu
Requires-Python: >=3.7,<4.0
Classifier: Programming Language :: Python :: 3
Classifier: Programming Language :: Python :: 3.7
Classifier: Programming Language :: Python :: 3.8
Requires-Dist: aif360 (>=0.3.0,<0.4.0)
Requires-Dist: pandas (>=1.0.5,<2.0.0)
Requires-Dist: scikit-learn (>=0.23.1,<0.24.0)
